[
    {
        "id": "fingerprint.findPatient",
        "instanceOf": "coreapps.template.findPatient",
        "description": "Patient search by fingerprint that goes to the patient dashboard",
        "order": 2,
        "extensions": [
            {
                "id": "coreapps.activeVisitsHomepageLink",
                "extensionPointId": "org.openmrs.referenceapplication.homepageLink",
                "type": "link",
                "label": "Find Patient by FingerPrint",
                "url": "fingerprint/findpatient/findPatient.page?app=fingerprint.findPatient",
                "icon": "icon-search",
                "requiredPrivilege": "App: fingerprint.findPatient"
            }
        ]
    }
]